reserve_it/__init__.py
reserve_it/cli.py
reserve_it/app/__init__.py
reserve_it/app/build_app.py
reserve_it/app/calendar_service.py
reserve_it/app/clear_calendar.py
reserve_it/app/database.py
reserve_it/app/reminders.py
reserve_it/app/route_helpers.py
reserve_it/app/utils.py
reserve_it/app/templates/response.html
reserve_it/example/.gitignore
reserve_it/example/app-config.yaml
reserve_it/example/mkdocs.yml
reserve_it/example/server_example.py
reserve_it/example/docs/readme.md
reserve_it/example/resource-configs/1-chargers.yaml
reserve_it/example/resource-configs/2-courts.yaml
reserve_it/example/resource-configs/courts.jpg
reserve_it/mkdocs_abuse/__init__.py
reserve_it/mkdocs_abuse/plugin.py
reserve_it/mkdocs_abuse/assets/reserve-it.css
reserve_it/mkdocs_abuse/assets/theme-tweaks.css
reserve_it/mkdocs_abuse/templates/form_page.md.j2
reserve_it/mkdocs_abuse/templates/ri_base.html
reserve_it/mkdocs_abuse/templates/ri_form.html
reserve_it/models/__init__.py
reserve_it/models/app_config.py
reserve_it/models/field_types.py
reserve_it/models/reservation.py
reserve_it/models/reservation_request.py
reserve_it/models/resource_config.py
reserve_it-1.0.0.dist-info/licenses/LICENSE
reserve_it-1.0.0.dist-info/METADATA
reserve_it-1.0.0.dist-info/WHEEL
reserve_it-1.0.0.dist-info/entry_points.txt
reserve_it-1.0.0.dist-info/top_level.txt
reserve_it-1.0.0.dist-info/RECORD
