Metadata-Version: 2.4
Name: reserve-it
Version: 1.0.0
Summary: A dead-simple reservation system web app framework, built on Google Calendar and Mkdocs-Material, implemented as a Mkdocs plugin.
Author-email: joshhubert-dsp <102703352+joshhubert-dsp@users.noreply.github.com>
Project-URL: Repository, https://github.com/joshhubert-dsp/reserve-it
Project-URL: Issues, https://github.com/joshhubert-dsp/reserve-it/issues
Project-URL: Documentation, https://joshhubert-dsp.github.io/reserve-it
Classifier: Development Status :: 4 - Beta
Classifier: Environment :: Web Environment
Classifier: Framework :: MkDocs
Classifier: Intended Audience :: Developers
Classifier: Natural Language :: English
Classifier: Operating System :: OS Independent
Classifier: Programming Language :: Python :: 3
Classifier: Programming Language :: Python :: 3.12
Classifier: Programming Language :: Python :: 3.13
Classifier: Topic :: Internet :: WWW/HTTP
Classifier: Topic :: Office/Business :: Scheduling
Classifier: Topic :: Software Development :: Libraries :: Application Frameworks
Requires-Python: <3.14,>=3.12
License-File: LICENSE
Requires-Dist: apscheduler>=3.11.1
Requires-Dist: colorama>=0.4.6
Requires-Dist: devtools>=0.12.2
Requires-Dist: fastapi>=0.121.2
Requires-Dist: gcsa>=2.6.0
Requires-Dist: jinja2>=3.1.6
Requires-Dist: loguru>=0.7.3
Requires-Dist: mkdocs-material>=9.7.1
Requires-Dist: pillow>=12.0.0
Requires-Dist: pydantic-settings>=2.12.0
Requires-Dist: pydantic[email]>=2.12.4
Requires-Dist: python-multipart>=0.0.20
Requires-Dist: pyyaml>=6.0.3
Requires-Dist: rich>=14.2.0
Requires-Dist: sqlmodel>=0.0.27
Requires-Dist: typer>=0.21.1
Requires-Dist: uvicorn>=0.38.0
Dynamic: license-file
